{
	"$schema": "https://schemas.wp.org/trunk/theme.json",
	"version": 3,
	"title": "Dark: Yellow base",
	"settings": {
		"color": {
			"palette": [
				{
					"slug": "unitone-accent",
					"color": "#a16207",
					"name": "Accent"
				},
				{
					"slug": "unitone-text-black",
					"color": "var(--unitone--color--text-immutable)",
					"name": "Text (Black / Immutable)"
				},
				{
					"slug": "unitone-background",
					"color": "var(--unitone--color--background)",
					"name": "Background"
				},
				{
					"slug": "unitone-text",
					"color": "var(--unitone--color--text)",
					"name": "Text"
				},
				{
					"slug": "unitone-background-alt",
					"color": "var(--unitone--color--background-alt)",
					"name": "Background Alt"
				},
				{
					"slug": "unitone-text-alt",
					"color": "var(--unitone--color--text-alt)",
					"name": "Text Alt"
				},
				{
					"slug": "unitone-pale-gray",
					"color": "color-mix(in srgb, #272727 98%, #a16207)",
					"name": "Pale Gray"
				},
				{
					"slug": "unitone-bright-gray",
					"color": "color-mix(in srgb, #2f2f2f 98%, #a16207)",
					"name": "Bright Gray"
				},
				{
					"slug": "unitone-light-gray",
					"color": "color-mix(in srgb, #3d3d3d 98%, #a16207)",
					"name": "Light Gray"
				},
				{
					"slug": "unitone-gray",
					"color": "color-mix(in srgb, #575757 98%, #a16207)",
					"name": "Gray"
				},
				{
					"slug": "unitone-dark-gray",
					"color": "color-mix(in srgb, #7b7b7b 98%, #a16207)",
					"name": "Dark Gray"
				},
				{
					"slug": "unitone-heavy-gray",
					"color": "color-mix(in srgb, #a7a7a7 98%, #a16207)",
					"name": "Heavy Gray"
				},
				{
					"slug": "unitone-inherit",
					"color": "inherit",
					"name": "inherit"
				},
				{
					"slug": "unitone-current",
					"color": "currentColor",
					"name": "currentColor"
				},
				{
					"slug": "unitone-transparent",
					"color": "transparent",
					"name": "transparent"
				}
			]
		}
	},
	"styles": {
		"color": {
			"background": "color-mix(in srgb, var(--unitone--color--text-immutable) 98%, #a16207)",
			"text": "#fff"
		},
		"elements": {
			"link": {
				"color": {
					"text": "#fff"
				}
			}
		}
	}
}
